cosmospy/__init__.py
cosmospy/_transaction.py
cosmospy/_wallet.py
cosmospy/py.typed
cosmospy/typing.py
cosmospy-6.0.0.dist-info/LICENSE
cosmospy-6.0.0.dist-info/WHEEL
cosmospy-6.0.0.dist-info/METADATA
cosmospy-6.0.0.dist-info/RECORD
