Metadata-Version: 2.1
Name: cosmospy
Version: 6.0.0
Summary: Tools for Cosmos wallet management and offline transaction signing
Home-page: https://github.com/hukkinj1/cosmospy
License: MIT
Keywords: cosmos,blockchain,atom,cryptocurrency
Author: hukkinj1
Author-email: hukkinj1@users.noreply.github.com
Requires-Python: >=3.6.1,<4.0.0
Classifier: Intended Audience :: Developers
Classifier: License :: OSI Approved :: MIT License
Classifier: Natural Language :: English
Classifier: Programming Language :: Python :: 3
Classifier: Programming Language :: Python :: 3.7
Classifier: Programming Language :: Python :: 3.8
Classifier: Programming Language :: Python :: 3.9
Classifier: Topic :: Software Development :: Libraries :: Python Modules
Classifier: Typing :: Typed
Requires-Dist: bech32 (>=1.1.0)
Requires-Dist: ecdsa (>=0.14.0)
Requires-Dist: hdwallets (>=0.1.0)
Requires-Dist: mnemonic (>=0.19)
Requires-Dist: typing-extensions (>=3.7.4,<4.0.0); python_version < "3.8"
Project-URL: Changelog, https://github.com/hukkinj1/cosmospy/blob/master/CHANGELOG.md
Project-URL: Repository, https://github.com/hukkinj1/cosmospy
